autotel/__init__.py
autotel/__version__.py
autotel/baggage_span_processor.py
autotel/circuit_breaker.py
autotel/config.py
autotel/context.py
autotel/db.py
autotel/debug.py
autotel/decorators.py
autotel/env_config.py
autotel/events.py
autotel/exporters.py
autotel/functional.py
autotel/helpers.py
autotel/http.py
autotel/init.py
autotel/logging.py
autotel/mcp.py
autotel/metrics.py
autotel/openllmetry.py
autotel/operation_context.py
autotel/pii_redaction.py
autotel/processors.py
autotel/py.typed
autotel/rate_limiter.py
autotel/sampling.py
autotel/semantic_helpers.py
autotel/serverless.py
autotel/shutdown.py
autotel/subscribers.py
autotel/trace_helpers.py
autotel/tracer_provider.py
autotel/track.py
autotel/validation.py
autotel/integrations/__init__.py
autotel/integrations/django.py
autotel/integrations/fastapi.py
autotel/integrations/flask.py
autotel/presets/__init__.py
autotel/presets/datadog.py
autotel/presets/honeycomb.py
autotel/subscribers/__init__.py
autotel/subscribers/base.py
autotel/subscribers/posthog.py
autotel/subscribers/slack.py
autotel/subscribers/streaming.py
autotel/subscribers/webhook.py
autotel/testing/__init__.py
autotel/testing/helpers.py
autotel-0.2.0.dist-info/METADATA
autotel-0.2.0.dist-info/WHEEL
autotel-0.2.0.dist-info/licenses/LICENSE
autotel-0.2.0.dist-info/RECORD
