Metadata-Version: 2.4
Name: autotel
Version: 0.2.0
Summary: Write One, Observe Everywhere: OpenTelemetry for Python
Project-URL: Homepage, https://github.com/jagreehal/autotel-python
Project-URL: Documentation, https://github.com/jagreehal/autotel-python#readme
Project-URL: Repository, https://github.com/jagreehal/autotel-python
Project-URL: Issues, https://github.com/jagreehal/autotel-python/issues
Author-email: Jag Reehal <jag@jagreehal.com>
License: MIT
License-File: LICENSE
Keywords: distributed-tracing,instrumentation,monitoring,observability,opentelemetry,otel,telemetry,tracing
Classifier: Development Status :: 4 - Beta
Classifier: Intended Audience :: Developers
Classifier: License :: OSI Approved :: MIT License
Classifier: Programming Language :: Python :: 3
Classifier: Programming Language :: Python :: 3.10
Classifier: Programming Language :: Python :: 3.11
Classifier: Programming Language :: Python :: 3.12
Classifier: Programming Language :: Python :: 3.13
Classifier: Topic :: Software Development :: Libraries :: Python Modules
Classifier: Topic :: System :: Monitoring
Classifier: Typing :: Typed
Requires-Python: >=3.10
Requires-Dist: opentelemetry-api>=1.38.0
Requires-Dist: opentelemetry-exporter-otlp>=1.38.0
Requires-Dist: opentelemetry-sdk>=1.38.0
Requires-Dist: pydantic>=2.12.0
Requires-Dist: typing-extensions>=4.12.0
Provides-Extra: all
Requires-Dist: httpx>=0.28.0; extra == 'all'
Requires-Dist: ollama>=0.6.0; extra == 'all'
Requires-Dist: opentelemetry-instrumentation-django>=0.47b0; extra == 'all'
Requires-Dist: opentelemetry-instrumentation-fastapi>=0.47b0; extra == 'all'
Requires-Dist: opentelemetry-instrumentation-flask>=0.47b0; extra == 'all'
Requires-Dist: pydantic-ai>=1.19.0; extra == 'all'
Requires-Dist: structlog>=25.5.0; extra == 'all'
Provides-Extra: dev
Requires-Dist: build>=1.0.0; extra == 'dev'
Requires-Dist: fastapi>=0.121.0; extra == 'dev'
Requires-Dist: httpx>=0.28.0; extra == 'dev'
Requires-Dist: mypy>=1.18.0; extra == 'dev'
Requires-Dist: pytest-asyncio>=1.3.0; extra == 'dev'
Requires-Dist: pytest-cov>=7.0.0; extra == 'dev'
Requires-Dist: pytest>=9.0.0; extra == 'dev'
Requires-Dist: ruff>=0.14.0; extra == 'dev'
Requires-Dist: twine>=5.0.0; extra == 'dev'
Provides-Extra: django
Requires-Dist: opentelemetry-instrumentation-django>=0.47b0; extra == 'django'
Provides-Extra: events
Requires-Dist: httpx>=0.28.0; extra == 'events'
Provides-Extra: fastapi
Requires-Dist: opentelemetry-instrumentation-fastapi>=0.47b0; extra == 'fastapi'
Provides-Extra: flask
Requires-Dist: opentelemetry-instrumentation-flask>=0.47b0; extra == 'flask'
Provides-Extra: logging
Requires-Dist: structlog>=25.5.0; extra == 'logging'
Provides-Extra: pydantic-ai
Requires-Dist: ollama>=0.6.0; extra == 'pydantic-ai'
Requires-Dist: pydantic-ai>=1.19.0; extra == 'pydantic-ai'
